upload2sf/__init__.py
upload2sf/load_environment_variables.py
upload2sf/sf_utils.py
upload2sf-0.1.4.dist-info/METADATA
upload2sf-0.1.4.dist-info/WHEEL
upload2sf-0.1.4.dist-info/top_level.txt
upload2sf-0.1.4.dist-info/RECORD
