Metadata-Version: 2.1
Name: upload2sf
Version: 0.1.4
Summary: A small wrapper to upload files to Snowflake
Author-email: Paul Ogier <ogier.paul@gmail.com>
Project-URL: homepage, https://github.com/ogierpaul/upload2sf
Classifier: Programming Language :: Python :: 3
Classifier: License :: OSI Approved :: MIT License
Classifier: Operating System :: OS Independent
Requires-Python: >=3.7
